jupyterlab_daisy/__init__.py
jupyterlab_daisy/_version.py
jupyterlab_daisy/handlers.py
jupyterlab_daisy/tests/__init__.py
jupyterlab_daisy/tests/test_handlers.py
jupyterlab_daisy-1.0.9.data/data/etc/jupyter/jupyter_notebook_config.d/jupyterlab_daisy.json
jupyterlab_daisy-1.0.9.data/data/etc/jupyter/jupyter_server_config.d/jupyterlab_daisy.json
jupyterlab_daisy-1.0.9.data/data/share/jupyter/labextensions/jupyterlab_daisy/build_log.json
jupyterlab_daisy-1.0.9.data/data/share/jupyter/labextensions/jupyterlab_daisy/package.json
jupyterlab_daisy-1.0.9.data/data/share/jupyter/labextensions/jupyterlab_daisy/schemas/jupyterlab_daisy/package.json.orig
jupyterlab_daisy-1.0.9.data/data/share/jupyter/labextensions/jupyterlab_daisy/schemas/jupyterlab_daisy/plugin.json
jupyterlab_daisy-1.0.9.data/data/share/jupyter/labextensions/jupyterlab_daisy/static/lib_index_js.1e66647cf90c25b3f7a9.js
jupyterlab_daisy-1.0.9.data/data/share/jupyter/labextensions/jupyterlab_daisy/static/lib_index_js.1e66647cf90c25b3f7a9.js.map
jupyterlab_daisy-1.0.9.data/data/share/jupyter/labextensions/jupyterlab_daisy/static/lib_index_js.4f4fa3af7a11afbd7f4b.js
jupyterlab_daisy-1.0.9.data/data/share/jupyter/labextensions/jupyterlab_daisy/static/lib_index_js.4f4fa3af7a11afbd7f4b.js.map
jupyterlab_daisy-1.0.9.data/data/share/jupyter/labextensions/jupyterlab_daisy/static/lib_index_js.67583a167c285ec211e1.js
jupyterlab_daisy-1.0.9.data/data/share/jupyter/labextensions/jupyterlab_daisy/static/lib_index_js.67583a167c285ec211e1.js.map
jupyterlab_daisy-1.0.9.data/data/share/jupyter/labextensions/jupyterlab_daisy/static/lib_index_js.7e1ca0d49c947a4158f3.js
jupyterlab_daisy-1.0.9.data/data/share/jupyter/labextensions/jupyterlab_daisy/static/lib_index_js.7e1ca0d49c947a4158f3.js.map
jupyterlab_daisy-1.0.9.data/data/share/jupyter/labextensions/jupyterlab_daisy/static/lib_index_js.91ec830588471c13de2c.js
jupyterlab_daisy-1.0.9.dist-info/METADATA
jupyterlab_daisy-1.0.9.dist-info/WHEEL
jupyterlab_daisy-1.0.9.dist-info/licenses/LICENSE
jupyterlab_daisy-1.0.9.dist-info/RECORD
