Metadata-Version: 2.1
Name: jupyterlab_daisy
Version: 1.0.9
Summary: Jupyter plugin for Daisy
Project-URL: Homepage, https://github.com/Archer6621/jupyterlab-daisy
Project-URL: Bug Tracker, https://github.com/Archer6621/jupyterlab-daisy/issues
Project-URL: Repository, https://github.com/Archer6621/jupyterlab-daisy.git
Author-email: Shaad Alaka <shaad1@live.nl>
License: BSD 3-Clause License
License-File: LICENSE
Classifier: Framework :: Jupyter
Classifier: Framework :: Jupyter :: JupyterLab
Classifier: Framework :: Jupyter :: JupyterLab :: 3
Classifier: Framework :: Jupyter :: JupyterLab :: Extensions
Classifier: Framework :: Jupyter :: JupyterLab :: Extensions :: Prebuilt
Classifier: License :: OSI Approved :: BSD License
Classifier: Programming Language :: Python
Classifier: Programming Language :: Python :: 3
Classifier: Programming Language :: Python :: 3.7
Classifier: Programming Language :: Python :: 3.8
Classifier: Programming Language :: Python :: 3.9
Classifier: Programming Language :: Python :: 3.10
Classifier: Programming Language :: Python :: 3.11
Requires-Python: >=3.7
Requires-Dist: jupyter-server==1.8
Requires-Dist: requests>=2.28.2
Provides-Extra: test
Requires-Dist: coverage; extra == 'test'
Requires-Dist: pytest; extra == 'test'
Requires-Dist: pytest-asyncio; extra == 'test'
Requires-Dist: pytest-cov; extra == 'test'
Requires-Dist: pytest-jupyter[server]>=0.6.0; extra == 'test'
